geoip2_data/__init__.py
geoip2_data/files.py
geoip2_data/version.py
geoip2_data/data/GeoLite2-ASN.mmdb
geoip2_data/data/GeoLite2-City.mmdb
geoip2_data/data/GeoLite2-Country.mmdb
geoip2_data-1.0.2.dist-info/METADATA
geoip2_data-1.0.2.dist-info/WHEEL
geoip2_data-1.0.2.dist-info/top_level.txt
geoip2_data-1.0.2.dist-info/RECORD
