Metadata-Version: 2.1
Name: geoip2-data
Version: 1.0.2
Summary: Show how to structure a Python project.
Home-page: https://github.com/SoundOn/geoip2-data
Author: SoundOn
Author-email: dev@soundon.fm
License: MIT
Platform: UNKNOWN
Classifier: Development Status :: 5 - Production/Stable
Classifier: Intended Audience :: Science/Research
Classifier: Programming Language :: Python :: 2.7
Classifier: Programming Language :: Python :: 3.6
